pyHiCTools/__init__.py
pyHiCTools/deduplicate.py
pyHiCTools/digest.py
pyHiCTools/extract.py
pyHiCTools/filter.py
pyHiCTools/main.py
pyHiCTools/map.py
pyHiCTools/process.py
pyHiCTools/truncate.py
pyHiCTools/valid_pair.py
pyHiCTools/version.py
pyHiCTools-2.1.0.data/scripts/pyHiCTools
pyHiCTools-2.1.0.dist-info/LICENSE
pyHiCTools-2.1.0.dist-info/METADATA
pyHiCTools-2.1.0.dist-info/WHEEL
pyHiCTools-2.1.0.dist-info/top_level.txt
pyHiCTools-2.1.0.dist-info/RECORD
